[
  {
    "ten": "Chơi cờ ca rô",
    "icon": "Game/GameCaRo.png",
    "duongdan": "Game/GameCaRo.html"
  },
  {
    "ten": "Luyện gõ bàn phím",
    "icon": "Game/GameMayTu.png",
    "duongdan": "Game/GameMayTu.html"
  },
  {
    "ten": "Trở Thành Pháo Thủ",
    "icon": "Game/GamePhaoThu.png",
    "duongdan": "Game/GamePhaoThu.html"
  },
  {
    "ten": "Sắp xếp đỗ Xe",
    "icon": "Game/1GameDoXe.JPG",
    "duongdan": "https://toytheater.com/parking.php"
  },
  {
    "ten": "Cờ Vua",
    "icon": "Game/1covua.png",
    "duongdan": "https://toytheater.com/chess.php"
  },
  {
    "ten": "Phóng phi tiêu",
    "icon": "Game/1phongphitieu.jpg",
    "duongdan": "https://toytheater.com/darts.php"
  }
]
